AnzhuoYingyongAnquanZhinanZhongwenban/README.md
AnzhuoYingyongAnquanZhinanZhongwenban/__init__.py
AnzhuoYingyongAnquanZhinanZhongwenban/__main__.py
AnzhuoYingyongAnquanZhinanZhongwenban/file.epub
AnzhuoYingyongAnquanZhinanZhongwenban/index.html
AnzhuoYingyongAnquanZhinanZhongwenban/css/__init__.py
AnzhuoYingyongAnquanZhinanZhongwenban/css/annotations.css
AnzhuoYingyongAnquanZhinanZhongwenban/css/main.css
AnzhuoYingyongAnquanZhinanZhongwenban/css/normalize.css
AnzhuoYingyongAnquanZhinanZhongwenban/css/popup.css
AnzhuoYingyongAnquanZhinanZhongwenban/font/__init__.py
AnzhuoYingyongAnquanZhinanZhongwenban/font/fontello.eot
AnzhuoYingyongAnquanZhinanZhongwenban/font/fontello.svg
AnzhuoYingyongAnquanZhinanZhongwenban/font/fontello.ttf
AnzhuoYingyongAnquanZhinanZhongwenban/font/fontello.woff
AnzhuoYingyongAnquanZhinanZhongwenban/img/__init__.py
AnzhuoYingyongAnquanZhinanZhongwenban/img/annotator-glyph-sprite.png
AnzhuoYingyongAnquanZhinanZhongwenban/img/annotator-icon-sprite.png
AnzhuoYingyongAnquanZhinanZhongwenban/img/apple-touch-icon.png
AnzhuoYingyongAnquanZhinanZhongwenban/img/cancelfullscreen.png
AnzhuoYingyongAnquanZhinanZhongwenban/img/close.png
AnzhuoYingyongAnquanZhinanZhongwenban/img/fullscreen.png
AnzhuoYingyongAnquanZhinanZhongwenban/img/loader.gif
AnzhuoYingyongAnquanZhinanZhongwenban/img/menu-icon.png
AnzhuoYingyongAnquanZhinanZhongwenban/img/save.png
AnzhuoYingyongAnquanZhinanZhongwenban/img/saved.png
AnzhuoYingyongAnquanZhinanZhongwenban/img/settings-s.png
AnzhuoYingyongAnquanZhinanZhongwenban/img/settings.png
AnzhuoYingyongAnquanZhinanZhongwenban/img/star.png
AnzhuoYingyongAnquanZhinanZhongwenban/js/__init__.py
AnzhuoYingyongAnquanZhinanZhongwenban/js/epub.js
AnzhuoYingyongAnquanZhinanZhongwenban/js/epub.min.js
AnzhuoYingyongAnquanZhinanZhongwenban/js/epub.min.map
AnzhuoYingyongAnquanZhinanZhongwenban/js/hooks.min.js
AnzhuoYingyongAnquanZhinanZhongwenban/js/hooks.min.map
AnzhuoYingyongAnquanZhinanZhongwenban/js/reader.js
anzhuo_yingyong_anquan_zhinan_zhongwenban-2024.3.3.0.dist-info/METADATA
anzhuo_yingyong_anquan_zhinan_zhongwenban-2024.3.3.0.dist-info/WHEEL
anzhuo_yingyong_anquan_zhinan_zhongwenban-2024.3.3.0.dist-info/entry_points.txt
anzhuo_yingyong_anquan_zhinan_zhongwenban-2024.3.3.0.dist-info/top_level.txt
anzhuo_yingyong_anquan_zhinan_zhongwenban-2024.3.3.0.dist-info/RECORD
